cometblue_lite/__init__.py
cometblue_lite/cometblue.py
cometblue_lite-0.4.1.dist-info/LICENSE
cometblue_lite-0.4.1.dist-info/METADATA
cometblue_lite-0.4.1.dist-info/WHEEL
cometblue_lite-0.4.1.dist-info/top_level.txt
cometblue_lite-0.4.1.dist-info/RECORD
