Metadata-Version: 2.1
Name: cometblue-lite
Version: 0.4.1
Summary: Module for Eurotronic Comet Blue thermostats
Home-page: https://github.com/neffs/python-cometblue-lite
Author: David Kreitschmann
Maintainer: David Kreitschmann
License: MIT
Platform: UNKNOWN
Classifier: Programming Language :: Python :: 3
Classifier: License :: OSI Approved :: MIT License
Classifier: Operating System :: POSIX :: Linux
Classifier: Development Status :: 3 - Alpha
Requires-Python: >=3.4
License-File: LICENSE
Requires-Dist: bluepy (>=1.3)
